uberduckapi/__init__.py
uberduckapi-0.1.18.dist-info/WHEEL
uberduckapi-0.1.18.dist-info/METADATA
uberduckapi-0.1.18.dist-info/RECORD
