Metadata-Version: 2.1
Name: uberduckapi
Version: 0.1.18
Summary: Python wrapper for uberduck API
Home-page: https://github.com/CupOfGeo/uberduckapi
License: MIT
Author: George
Author-email: mazzeogeorge@gmail.com
Requires-Python: >=3.7,<4.0
Classifier: License :: OSI Approved :: MIT License
Classifier: Programming Language :: Python :: 3
Classifier: Programming Language :: Python :: 3.10
Classifier: Programming Language :: Python :: 3.7
Classifier: Programming Language :: Python :: 3.8
Classifier: Programming Language :: Python :: 3.9
Requires-Dist: polling (>=0.3.2,<0.4.0)
Requires-Dist: pydub (>=0.25.0,<0.26.0)
Requires-Dist: requests (>=2.26.0,<3.0.0)
Project-URL: Repository, https://github.com/CupOfGeo/uberduckapi
Project-URL: Uberduck, https://uberduck.ai
